the_retry/__init__.py
the_retry/retry.py
the_retry-0.1.1.dist-info/LICENSE
the_retry-0.1.1.dist-info/WHEEL
the_retry-0.1.1.dist-info/METADATA
the_retry-0.1.1.dist-info/RECORD
