Metadata-Version: 2.1
Name: the-retry
Version: 0.1.1
Summary: Retry decorator for both synchronous and asynchronous functions.
Home-page: https://gitlab.com/ramil.minnigaliev/the-retry
License: MIT
Keywords: decorator,retry,async-retry
Author: Ramil Minnigaliev
Author-email: minnigaliev-r@yandex.ru
Requires-Python: >=3.6,<4.0
Classifier: License :: OSI Approved :: MIT License
Classifier: Programming Language :: Python :: 3
Classifier: Programming Language :: Python :: 3.6
Classifier: Programming Language :: Python :: 3.7
Classifier: Programming Language :: Python :: 3.8
Classifier: Programming Language :: Python :: 3.9
Classifier: Programming Language :: Python :: 3.10
Project-URL: Repository, https://gitlab.com/ramil.minnigaliev/the-retry
